LICENSE
README.md
setup.py
./__init__.py
./pythonrest.py
./apigenerator/__init__.py
./apigenerator/a_Domain/SaMetaClass.py
./apigenerator/a_Domain/SaRowAttribute.py
./apigenerator/a_Domain/__init__.py
./apigenerator/b_Workers/ApiGeneratorWorker.py
./apigenerator/b_Workers/DatabaseFilesWorker.py
./apigenerator/b_Workers/DirectoryManager.py
./apigenerator/b_Workers/DomainMigrationHandler.py
./apigenerator/b_Workers/EnvironmentVariablesWorker.py
./apigenerator/b_Workers/MigrationHandler.py
./apigenerator/b_Workers/ModifierHandler.py
./apigenerator/b_Workers/ProjectFinalizer.py
./apigenerator/b_Workers/StarterWorker.py
./apigenerator/b_Workers/__init__.py
./apigenerator/e_Enumerables/Enumerables.py
./apigenerator/e_Enumerables/__init__.py
./apigenerator/f_Builders/FlaskAdminBuilder.py
./apigenerator/f_Builders/RedocBuilder.py
./apigenerator/f_Builders/SwaggerBuilder.py
./apigenerator/f_Builders/__init__.py
./apigenerator/g_Utils/OpenFileExeHandler.py
./apigenerator/g_Utils/StringAndFileHandler.py
./apigenerator/g_Utils/YamlAliasIgnore.py
./apigenerator/g_Utils/__init__.py
./apigenerator/resources/__init__.py
./apigenerator/resources/1 - Project/__init__.py
./apigenerator/resources/1 - Project/1 - BaseProject/__init__.py
./apigenerator/resources/1 - Project/1 - BaseProject/Project/README.md
./apigenerator/resources/1 - Project/1 - BaseProject/Project/__init__.py
./apigenerator/resources/1 - Project/1 - BaseProject/Project/app.py
./apigenerator/resources/1 - Project/1 - BaseProject/Project/requirements.txt
./apigenerator/resources/1 - Project/1 - BaseProject/Project/config/__init__.py
./apigenerator/resources/1 - Project/1 - BaseProject/Project/config/auth.html
./apigenerator/resources/1 - Project/1 - BaseProject/Project/config/swagger.yaml
./apigenerator/resources/1 - Project/1 - BaseProject/Project/src/__init__.py
./apigenerator/resources/1 - Project/1 - BaseProject/Project/src/a_Presentation/__init__.py
pythonrest3.egg-info/PKG-INFO
pythonrest3.egg-info/SOURCES.txt
pythonrest3.egg-info/dependency_links.txt
pythonrest3.egg-info/entry_points.txt
pythonrest3.egg-info/requires.txt
pythonrest3.egg-info/top_level.txt