Metadata-Version: 2.1
Name: pythonrest3
Version: 0.4.1
Summary: A CLI tool that generates a complete API using a connection string for supported databases: mysql, mssql, mariadb and postgres
Author: Seven Technologies Cloud
Author-email: admin@seventechnologies.cloud
Maintainer: Seven Technologies Cloud
Keywords: api,rest api,database,python,mysql,mssql,postgres,aurora,mariadb
License-File: LICENSE
